   {
      "lvTypePathStr":"team",
      "lvIDPathStr":"822861",
      "lvTypeLabelStr":"\/ HGW Hofweier",
      "dataList":[
         {
            "lvTypeNext":"",
            "lvIDNext":0,
            "levelTypeLabel":"",
            "gID":"5385821",
            "gNo":"102101",
            "gClassID":"80846",
            "gClassSname":"M-SL-AB",
            "gDate":"25.09.21",
            "gTime":"19:30",
            "gGymnasiumID":"540",
            "gGymnasiumNo":"10026",
            "gGymnasiumName":"Hohberghalle-Niederschopfheim",
            "gGymnasiumPostal":"77749",
            "gGymnasiumTown":"Hohberg",
            "gGymnasiumStreet":"Laugasserfeld 1",
            "gHomeTeam":"HGW Hofweier",
            "gGuestTeam":"TuS Ottenheim",
            "gLive":false,
            "gTickerToken":" ",
            "gHomeGoals":"24",
            "gGuestGoals":"21",
            "gHomeGoals_1":" ",
            "gGuestGoals_1":" ",
            "gHomePoints":"2",
            "gGuestPoints":"0",
            "gComment":" ",
            "gReferee":" "
         },
         {
            "lvTypeNext":"",
            "lvIDNext":0,
            "levelTypeLabel":"",
            "gID":"5385831",
            "gNo":"102103",
            "gClassID":"80846",
            "gClassSname":"M-SL-AB",
            "gDate":"08.10.21",
            "gTime":"20:00",
            "gGymnasiumID":"540",
            "gGymnasiumNo":"10026",
            "gGymnasiumName":"Hohberghalle-Niederschopfheim",
            "gGymnasiumPostal":"77749",
            "gGymnasiumTown":"Hohberg",
            "gGymnasiumStreet":"Laugasserfeld 1",
            "gHomeTeam":"HGW Hofweier",
            "gGuestTeam":"HTV Mei\u00dfenheim",
            "gLive":false,
            "gTickerToken":" ",
            "gHomeGoals":"36",
            "gGuestGoals":"25",
            "gHomeGoals_1":" ",
            "gGuestGoals_1":" ",
            "gHomePoints":"2",
            "gGuestPoints":"0",
            "gComment":" ",
            "gReferee":" "
         },
         {
            "lvTypeNext":"",
            "lvIDNext":0,
            "levelTypeLabel":"",
            "gID":"5385836",
            "gNo":"102104",
            "gClassID":"80846",
            "gClassSname":"M-SL-AB",
            "gDate":"23.10.21",
            "gTime":"17:30",
            "gGymnasiumID":"687",
            "gGymnasiumNo":"10022",
            "gGymnasiumName":"Rheintalhalle",
            "gGymnasiumPostal":"76532",
            "gGymnasiumTown":"Sandweier",
            "gGymnasiumStreet":"Rheintalstra\u00dfe 34",
            "gHomeTeam":"TVS Bad-Bad 2",
            "gGuestTeam":"HGW Hofweier",
            "gLive":false,
            "gTickerToken":" ",
            "gHomeGoals":"24",
            "gGuestGoals":"28",
            "gHomeGoals_1":" ",
            "gGuestGoals_1":" ",
            "gHomePoints":"0",
            "gGuestPoints":"2",
            "gComment":" ",
            "gReferee":" "
         },
         {
            "lvTypeNext":"",
            "lvIDNext":0,
            "levelTypeLabel":"",
            "gID":"5385856",
            "gNo":"102108",
            "gClassID":"80846",
            "gClassSname":"M-SL-AB",
            "gDate":"20.11.21",
            "gTime":"19:30",
            "gGymnasiumID":"540",
            "gGymnasiumNo":"10026",
            "gGymnasiumName":"Hohberghalle-Niederschopfheim",
            "gGymnasiumPostal":"77749",
            "gGymnasiumTown":"Hohberg",
            "gGymnasiumStreet":"Laugasserfeld 1",
            "gHomeTeam":"HGW Hofweier",
            "gGuestTeam":"TVS Bad-Bad 2",
            "gLive":false,
            "gTickerToken":" ",
            "gHomeGoals":"32",
            "gGuestGoals":"25",
            "gHomeGoals_1":" ",
            "gGuestGoals_1":" ",
            "gHomePoints":"2",
            "gGuestPoints":"0",
            "gComment":" ",
            "gReferee":" "
         },
         {
            "lvTypeNext":"",
            "lvIDNext":0,
            "levelTypeLabel":"",
            "gID":"5385871",
            "gNo":"102111",
            "gClassID":"80846",
            "gClassSname":"M-SL-AB",
            "gDate":"15.01.22",
            "gTime":"20:00",
            "gGymnasiumID":"489",
            "gGymnasiumNo":"10043",
            "gGymnasiumName":"Rheinauenhalle",
            "gGymnasiumPostal":"77963",
            "gGymnasiumTown":"Schwanau-Ottenheim",
            "gGymnasiumStreet":"Weiblingsweg 2",
            "gHomeTeam":"TuS Ottenheim",
            "gGuestTeam":"HGW Hofweier",
            "gLive":false,
            "gTickerToken":" ",
            "gHomeGoals":"25",
            "gGuestGoals":"30",
            "gHomeGoals_1":" ",
            "gGuestGoals_1":" ",
            "gHomePoints":"0",
            "gGuestPoints":"2",
            "gComment":" ",
            "gReferee":" "
         },
         {
            "lvTypeNext":"",
            "lvIDNext":0,
            "levelTypeLabel":"",
            "gID":"5385866",
            "gNo":"102110",
            "gClassID":"80846",
            "gClassSname":"M-SL-AB",
            "gDate":"19.02.22",
            "gTime":"20:00",
            "gGymnasiumID":"692",
            "gGymnasiumNo":"10031",
            "gGymnasiumName":"Sporthalle",
            "gGymnasiumPostal":"77974",
            "gGymnasiumTown":"Mei\u00dfenheim",
            "gGymnasiumStreet":"M\u00fchlstra\u00dfe",
            "gHomeTeam":"HTV Mei\u00dfenheim",
            "gGuestTeam":"HGW Hofweier",
            "gLive":false,
            "gTickerToken":" ",
            "gHomeGoals":"24",
            "gGuestGoals":"39",
            "gHomeGoals_1":"8",
            "gGuestGoals_1":"21",
            "gHomePoints":"0",
            "gGuestPoints":"2",
            "gComment":" ",
            "gReferee":" "
         },
         {
            "lvTypeNext":"",
            "lvIDNext":0,
            "levelTypeLabel":"",
            "gID":"5385946",
            "gNo":"102126",
            "gClassID":"80846",
            "gClassSname":"M-SL-AB",
            "gDate":"05.03.22",
            "gTime":"19:30",
            "gGymnasiumID":"540",
            "gGymnasiumNo":"10026",
            "gGymnasiumName":"Hohberghalle-Niederschopfheim",
            "gGymnasiumPostal":"77749",
            "gGymnasiumTown":"Hohberg",
            "gGymnasiumStreet":"Laugasserfeld 1",
            "gHomeTeam":"HGW Hofweier",
            "gGuestTeam":"SG Ohlsb\/Elger",
            "gLive":false,
            "gTickerToken":" ",
            "gHomeGoals":"30",
            "gGuestGoals":"23",
            "gHomeGoals_1":"14",
            "gGuestGoals_1":"12",
            "gHomePoints":"2",
            "gGuestPoints":"0",
            "gComment":" ",
            "gReferee":" "
         },
         {
            "lvTypeNext":"",
            "lvIDNext":0,
            "levelTypeLabel":"",
            "gID":"5386001",
            "gNo":"102137",
            "gClassID":"80846",
            "gClassSname":"M-SL-AB",
            "gDate":"26.03.22",
            "gTime":"19:30",
            "gGymnasiumID":"540",
            "gGymnasiumNo":"10026",
            "gGymnasiumName":"Hohberghalle-Niederschopfheim",
            "gGymnasiumPostal":"77749",
            "gGymnasiumTown":"Hohberg",
            "gGymnasiumStreet":"Laugasserfeld 1",
            "gHomeTeam":"HGW Hofweier",
            "gGuestTeam":"SG K\u00f6nd\/Tening 2",
            "gLive":false,
            "gTickerToken":" ",
            "gHomeGoals":"43",
            "gGuestGoals":"27",
            "gHomeGoals_1":"19",
            "gGuestGoals_1":"10",
            "gHomePoints":"2",
            "gGuestPoints":"0",
            "gComment":" ",
            "gReferee":" "
         },
         {
            "lvTypeNext":"",
            "lvIDNext":0,
            "levelTypeLabel":"",
            "gID":"5385971",
            "gNo":"102131",
            "gClassID":"80846",
            "gClassSname":"M-SL-AB",
            "gDate":"03.04.22",
            "gTime":"16:30",
            "gGymnasiumID":"540",
            "gGymnasiumNo":"10026",
            "gGymnasiumName":"Hohberghalle-Niederschopfheim",
            "gGymnasiumPostal":"77749",
            "gGymnasiumTown":"Hohberg",
            "gGymnasiumStreet":"Laugasserfeld 1",
            "gHomeTeam":"HGW Hofweier",
            "gGuestTeam":"TV Ehingen",
            "gLive":false,
            "gTickerToken":" ",
            "gHomeGoals":"36",
            "gGuestGoals":"36",
            "gHomeGoals_1":"16",
            "gGuestGoals_1":"13",
            "gHomePoints":"1",
            "gGuestPoints":"1",
            "gComment":" ",
            "gReferee":" "
         },
         {
            "lvTypeNext":"",
            "lvIDNext":0,
            "levelTypeLabel":"",
            "gID":"5386041",
            "gNo":"102145",
            "gClassID":"80846",
            "gClassSname":"M-SL-AB",
            "gDate":"09.04.22",
            "gTime":"20:00",
            "gGymnasiumID":"539",
            "gGymnasiumNo":"10091",
            "gGymnasiumName":"Eugen-Sch\u00e4dler-Halle",
            "gGymnasiumPostal":"78259",
            "gGymnasiumTown":"M\u00fchlhausen-Ehingen",
            "gGymnasiumStreet":"Obere Tiefe",
            "gHomeTeam":"TV Ehingen",
            "gGuestTeam":"HGW Hofweier",
            "gLive":false,
            "gTickerToken":" ",
            "gHomeGoals":"29",
            "gGuestGoals":"27",
            "gHomeGoals_1":"15",
            "gGuestGoals_1":"12",
            "gHomePoints":"2",
            "gGuestPoints":"0",
            "gComment":" ",
            "gReferee":" "
         },
         {
            "lvTypeNext":"",
            "lvIDNext":0,
            "levelTypeLabel":"",
            "gID":"5385991",
            "gNo":"102135",
            "gClassID":"80846",
            "gClassSname":"M-SL-AB",
            "gDate":"14.04.22",
            "gTime":"20:00",
            "gGymnasiumID":"604",
            "gGymnasiumNo":"10063",
            "gGymnasiumName":"Rheinmatthalle",
            "gGymnasiumPostal":"79365",
            "gGymnasiumTown":"Rheinhausen",
            "gGymnasiumStreet":"Hauptstra\u00dfe 100",
            "gHomeTeam":"TuS Oberhausen",
            "gGuestTeam":"HGW Hofweier",
            "gLive":false,
            "gTickerToken":" ",
            "gHomeGoals":"30",
            "gGuestGoals":"34",
            "gHomeGoals_1":"15",
            "gGuestGoals_1":"14",
            "gHomePoints":"0",
            "gGuestPoints":"2",
            "gComment":" ",
            "gReferee":" "
         },
         {
            "lvTypeNext":"",
            "lvIDNext":0,
            "levelTypeLabel":"",
            "gID":"5386066",
            "gNo":"102150",
            "gClassID":"80846",
            "gClassSname":"M-SL-AB",
            "gDate":"24.04.22",
            "gTime":"17:00",
            "gGymnasiumID":"495",
            "gGymnasiumNo":"10066",
            "gGymnasiumName":"Ludwig-Jahn-Halle",
            "gGymnasiumPostal":"79331",
            "gGymnasiumTown":"Teningen",
            "gGymnasiumStreet":"Ludwig-Jahn-Stra\u00dfe 5",
            "gHomeTeam":"SG K\u00f6nd\/Tening 2",
            "gGuestTeam":"HGW Hofweier",
            "gLive":false,
            "gTickerToken":" ",
            "gHomeGoals":"28",
            "gGuestGoals":"28",
            "gHomeGoals_1":"12",
            "gGuestGoals_1":"12",
            "gHomePoints":"1",
            "gGuestPoints":"1",
            "gComment":" ",
            "gReferee":" "
         },
         {
            "lvTypeNext":"",
            "lvIDNext":0,
            "levelTypeLabel":"",
            "gID":"5386081",
            "gNo":"102153",
            "gClassID":"80846",
            "gClassSname":"M-SL-AB",
            "gDate":"07.05.22",
            "gTime":"19:30",
            "gGymnasiumID":"540",
            "gGymnasiumNo":"10026",
            "gGymnasiumName":"Hohberghalle-Niederschopfheim",
            "gGymnasiumPostal":"77749",
            "gGymnasiumTown":"Hohberg",
            "gGymnasiumStreet":"Laugasserfeld 1",
            "gHomeTeam":"HGW Hofweier",
            "gGuestTeam":"TuS Oberhausen",
            "gLive":false,
            "gTickerToken":" ",
            "gHomeGoals":"35",
            "gGuestGoals":"26",
            "gHomeGoals_1":"18",
            "gGuestGoals_1":"12",
            "gHomePoints":"2",
            "gGuestPoints":"0",
            "gComment":" ",
            "gReferee":" "
         },
         {
            "lvTypeNext":"",
            "lvIDNext":0,
            "levelTypeLabel":"",
            "gID":"5386021",
            "gNo":"102141",
            "gClassID":"80846",
            "gClassSname":"M-SL-AB",
            "gDate":"14.05.22",
            "gTime":"20:00",
            "gGymnasiumID":"694",
            "gGymnasiumNo":"10035",
            "gGymnasiumName":"Otto-Kempf-Sporthalle",
            "gGymnasiumPostal":"77656",
            "gGymnasiumTown":"Offenburg-Elgersweier",
            "gGymnasiumStreet":"Sandackerweg",
            "gHomeTeam":"SG Ohlsb\/Elger",
            "gGuestTeam":"HGW Hofweier",
            "gLive":false,
            "gTickerToken":" ",
            "gHomeGoals":"27",
            "gGuestGoals":"27",
            "gHomeGoals_1":"15",
            "gGuestGoals_1":"15",
            "gHomePoints":"1",
            "gGuestPoints":"1",
            "gComment":" ",
            "gReferee":" "
         }
      ],
      "errCode":0
   }
